{
    "1": {
        "Id": 1,
        "Title": "消費したらすぐ補充！",
        "DisplayPriority": 1
    },
    "2": {
        "Id": 2,
        "Title": "データキャラです！",
        "DisplayPriority": 2
    },
    "3": {
        "Id": 3,
        "Title": "ハーレム・・・・・・?",
        "DisplayPriority": 3
    },
    "4": {
        "Id": 4,
        "Title": "詩絵先生の方言口座１",
        "DisplayPriority": 4
    },
    "5": {
        "Id": 5,
        "Title": "わかる人はわかる",
        "DisplayPriority": 5
    },
    "6": {
        "Id": 6,
        "Title": "お金ですませば問題なし",
        "DisplayPriority": 6
    },
    "7": {
        "Id": 7,
        "Title": "勝つまで、勝ちます",
        "DisplayPriority": 7
    },
    "8": {
        "Id": 8,
        "Title": "Liebe Kimono",
        "DisplayPriority": 8
    },
    "9": {
        "Id": 9,
        "Title": "♰黒き獣♰",
        "DisplayPriority": 9
    },
    "10": {
        "Id": 10,
        "Title": "【悲報】イキりーこ、不死鳥",
        "DisplayPriority": 10
    },
    "11": {
        "Id": 11,
        "Title": "よし！(わかってない)",
        "DisplayPriority": 11
    },
    "12": {
        "Id": 12,
        "Title": "鬼は見ている・・・・・・",
        "DisplayPriority": 12
    },
    "13": {
        "Id": 13,
        "Title": "愛の芽生え？",
        "DisplayPriority": 13
    },
    "14": {
        "Id": 14,
        "Title": "栄華の裏側",
        "DisplayPriority": 14
    },
    "15": {
        "Id": 15,
        "Title": "来たれ、愛の園！",
        "DisplayPriority": 15
    },
    "16": {
        "Id": 16,
        "Title": "何気ない発言が・・・・・・",
        "DisplayPriority": 16
    },
    "17": {
        "Id": 17,
        "Title": "ストロングフライデー",
        "DisplayPriority": 17
    },
    "18": {
        "Id": 18,
        "Title": "眠くなるまで熱中を・・・・・・",
        "DisplayPriority": 18
    },
    "19": {
        "Id": 19,
        "Title": "レトロラジオフリーク",
        "DisplayPriority": 19
    },
    "20": {
        "Id": 20,
        "Title": "久々のイベントで・・・・・・",
        "DisplayPriority": 20
    },
    "21": {
        "Id": 21,
        "Title": "UJAJ公式マスコット！",
        "DisplayPriority": 21
    },
    "22": {
        "Id": 22,
        "Title": "これは作りもの・・・・・・！",
        "DisplayPriority": 22
    },
    "23": {
        "Id": 23,
        "Title": "年齢は・・・・・・？",
        "DisplayPriority": 23
    },
    "24": {
        "Id": 24,
        "Title": "大好きなのは？",
        "DisplayPriority": 24
    },
    "25": {
        "Id": 25,
        "Title": "これも対策のため・・・・・・！",
        "DisplayPriority": 25
    }
}